Metadata-Version: 2.1
Name: DuckMapper
Version: 1.0.1
Summary: A tiny library to help you to convert classes to DTO and vice versa.
Home-page: https://github.com/lucascz37/DuckMapper
Author: Lucas A. Andrade
Author-email: luke.andrade99@gmail.com
License: MIT
Keywords: DTO conversor mapper classMapper DuckMapper
Platform: UNKNOWN
